djangoldp_conversation/__init__.py
djangoldp_conversation/admin.py
djangoldp_conversation/apps.py
djangoldp_conversation/factories.py
djangoldp_conversation/models.py
djangoldp_conversation/management/__init__.py
djangoldp_conversation/management/commands/__init__.py
djangoldp_conversation/management/commands/mock_conversation.py
djangoldp_conversation/migrations/0001_initial.py
djangoldp_conversation/migrations/0002_auto_20190917_1056.py
djangoldp_conversation/migrations/0003_auto_20200522_1521.py
djangoldp_conversation/migrations/0004_auto_20200610_1323.py
djangoldp_conversation/migrations/0005_auto_20200619_0817.py
djangoldp_conversation/migrations/0006_auto_20200723_1312.py
djangoldp_conversation/migrations/0007_auto_20200926_0911.py
djangoldp_conversation/migrations/0008_alter_conversation_urlid_alter_message_urlid.py
djangoldp_conversation/migrations/0009_add_timestamps_to_models.py
djangoldp_conversation/migrations/__init__.py
djangoldp_conversation-5.0.0.dist-info/METADATA
djangoldp_conversation-5.0.0.dist-info/WHEEL
djangoldp_conversation-5.0.0.dist-info/top_level.txt
djangoldp_conversation-5.0.0.dist-info/RECORD
