Metadata-Version: 2.4
Name: djangoldp_conversation
Version: 5.0.0
Summary: djangoldp package for conversation data models
Home-page: https://git.happy-dev.fr/startinblox/djangoldp-packages/djangoldp-conversations
Author: Startin'blox
Author-email: matthieu@happy-dev.fr
License: MIT
Requires-Dist: djangoldp~=5.0.0
Provides-Extra: dev
Requires-Dist: factory_boy>=2.11.0; extra == "dev"
